CHANGES.txt
LICENSE.txt
MANIFEST.in
README.txt
buildout.cfg
setup.py
eggs/BTrees-6.1-py3.10-win-amd64.egg/EGG-INFO/LICENSE.txt
eggs/BTrees-6.1-py3.10-win-amd64.egg/EGG-INFO/requires.txt
eggs/BTrees-6.1-py3.10-win-amd64.egg/EGG-INFO/top_level.txt
eggs/ZConfig-4.2-py3.10.egg/EGG-INFO/LICENSE.txt
eggs/ZConfig-4.2-py3.10.egg/EGG-INFO/entry_points.txt
eggs/ZConfig-4.2-py3.10.egg/EGG-INFO/requires.txt
eggs/ZConfig-4.2-py3.10.egg/EGG-INFO/top_level.txt
eggs/ZConfig-4.2-py3.10.egg/ZConfig/schemaless.txt
eggs/ZConfig-4.2-py3.10.egg/ZConfig/tests/input/non-ascii.txt
eggs/ZConfig-4.2-py3.10.egg/ZConfig/tests/library/README.txt
eggs/ZConfig-4.2-py3.10.egg/ZConfig/tests/zipsource/README.txt
eggs/cffi-1.17.1-py3.10-win-amd64.egg/EGG-INFO/entry_points.txt
eggs/cffi-1.17.1-py3.10-win-amd64.egg/EGG-INFO/requires.txt
eggs/cffi-1.17.1-py3.10-win-amd64.egg/EGG-INFO/top_level.txt
eggs/coverage-7.10.5-py3.10-win-amd64.egg/EGG-INFO/entry_points.txt
eggs/coverage-7.10.5-py3.10-win-amd64.egg/EGG-INFO/requires.txt
eggs/coverage-7.10.5-py3.10-win-amd64.egg/EGG-INFO/top_level.txt
eggs/coverage-7.10.5-py3.10-win-amd64.egg/EGG-INFO/licenses/LICENSE.txt
eggs/future-1.0.0-py3.10.egg/EGG-INFO/LICENSE.txt
eggs/future-1.0.0-py3.10.egg/EGG-INFO/entry_points.txt
eggs/future-1.0.0-py3.10.egg/EGG-INFO/top_level.txt
eggs/lxml-6.0.1-py3.10-win-amd64.egg/EGG-INFO/requires.txt
eggs/lxml-6.0.1-py3.10-win-amd64.egg/EGG-INFO/top_level.txt
eggs/lxml-6.0.1-py3.10-win-amd64.egg/EGG-INFO/licenses/LICENSE.txt
eggs/lxml-6.0.1-py3.10-win-amd64.egg/EGG-INFO/licenses/LICENSES.txt
eggs/lxml-6.0.1-py3.10-win-amd64.egg/lxml/isoschematron/resources/xsl/iso-schematron-xslt1/readme.txt
eggs/multipart-1.3.0-py3.10.egg/EGG-INFO/requires.txt
eggs/p01.checker-0.5.12-py3.10.egg/EGG-INFO/SOURCES.txt
eggs/p01.checker-0.5.12-py3.10.egg/EGG-INFO/dependency_links.txt
eggs/p01.checker-0.5.12-py3.10.egg/EGG-INFO/namespace_packages.txt
eggs/p01.checker-0.5.12-py3.10.egg/EGG-INFO/requires.txt
eggs/p01.checker-0.5.12-py3.10.egg/EGG-INFO/top_level.txt
eggs/p01.checker-0.5.12-py3.10.egg/p01/checker/checker.txt
eggs/p01.checker-0.5.12-py3.10.egg/p01/checker/sample/tab.txt
eggs/p01.checker-0.5.13-py3.10.egg/EGG-INFO/SOURCES.txt
eggs/p01.checker-0.5.13-py3.10.egg/EGG-INFO/dependency_links.txt
eggs/p01.checker-0.5.13-py3.10.egg/EGG-INFO/namespace_packages.txt
eggs/p01.checker-0.5.13-py3.10.egg/EGG-INFO/requires.txt
eggs/p01.checker-0.5.13-py3.10.egg/EGG-INFO/top_level.txt
eggs/p01.checker-0.5.13-py3.10.egg/p01/checker/checker.txt
eggs/p01.checker-0.5.13-py3.10.egg/p01/checker/sample/tab.txt
eggs/p01.checker-0.5.15-py3.10.egg/EGG-INFO/SOURCES.txt
eggs/p01.checker-0.5.15-py3.10.egg/EGG-INFO/dependency_links.txt
eggs/p01.checker-0.5.15-py3.10.egg/EGG-INFO/namespace_packages.txt
eggs/p01.checker-0.5.15-py3.10.egg/EGG-INFO/requires.txt
eggs/p01.checker-0.5.15-py3.10.egg/EGG-INFO/top_level.txt
eggs/p01.checker-0.5.15-py3.10.egg/p01/checker/checker.txt
eggs/p01.checker-0.5.15-py3.10.egg/p01/checker/sample/tab.txt
eggs/p01.recipe.setup-0.8.19-py3.10.egg/EGG-INFO/SOURCES.txt
eggs/p01.recipe.setup-0.8.19-py3.10.egg/EGG-INFO/dependency_links.txt
eggs/p01.recipe.setup-0.8.19-py3.10.egg/EGG-INFO/entry_points.txt
eggs/p01.recipe.setup-0.8.19-py3.10.egg/EGG-INFO/namespace_packages.txt
eggs/p01.recipe.setup-0.8.19-py3.10.egg/EGG-INFO/requires.txt
eggs/p01.recipe.setup-0.8.19-py3.10.egg/EGG-INFO/top_level.txt
eggs/p01.recipe.setup-0.8.19-py3.10.egg/p01/recipe/setup/README.txt
eggs/p01.recipe.setup-0.8.19-py3.10.egg/p01/recipe/setup/checker.txt
eggs/p01.recipe.setup-0.8.19-py3.10.egg/p01/recipe/setup/cmd.txt
eggs/p01.recipe.setup-0.8.19-py3.10.egg/p01/recipe/setup/copy.txt
eggs/p01.recipe.setup-0.8.19-py3.10.egg/p01/recipe/setup/download.txt
eggs/p01.recipe.setup-0.8.19-py3.10.egg/p01/recipe/setup/fetch.txt
eggs/p01.recipe.setup-0.8.19-py3.10.egg/p01/recipe/setup/i18n.txt
eggs/p01.recipe.setup-0.8.19-py3.10.egg/p01/recipe/setup/importchecker.txt
eggs/p01.recipe.setup-0.8.19-py3.10.egg/p01/recipe/setup/index.txt
eggs/p01.recipe.setup-0.8.19-py3.10.egg/p01/recipe/setup/mkdir.txt
eggs/p01.recipe.setup-0.8.19-py3.10.egg/p01/recipe/setup/mkfile.txt
eggs/p01.recipe.setup-0.8.19-py3.10.egg/p01/recipe/setup/paste.txt
eggs/p01.recipe.setup-0.8.19-py3.10.egg/p01/recipe/setup/script.txt
eggs/p01.recipe.setup-0.8.19-py3.10.egg/p01/recipe/setup/scripts.txt
eggs/p01.recipe.setup-0.8.19-py3.10.egg/p01/recipe/setup/supervisor.txt
eggs/p01.recipe.setup-0.8.19-py3.10.egg/p01/recipe/setup/template.txt
eggs/p01.recipe.setup-0.8.19-py3.10.egg/p01/recipe/setup/winservice.txt
eggs/persistent-6.1.1-py3.10-win-amd64.egg/EGG-INFO/LICENSE.txt
eggs/persistent-6.1.1-py3.10-win-amd64.egg/EGG-INFO/requires.txt
eggs/persistent-6.1.1-py3.10-win-amd64.egg/EGG-INFO/top_level.txt
eggs/polib-1.2.0-py3.10.egg/EGG-INFO/top_level.txt
eggs/pycparser-2.22-py3.10.egg/EGG-INFO/top_level.txt
eggs/pyflakes-2.1.1-py3.10.egg/EGG-INFO/entry_points.txt
eggs/pyflakes-2.1.1-py3.10.egg/EGG-INFO/top_level.txt
eggs/pyflakes-3.4.0-py3.10.egg/EGG-INFO/entry_points.txt
eggs/pyflakes-3.4.0-py3.10.egg/EGG-INFO/top_level.txt
eggs/python_gettext-5.0-py3.10.egg/EGG-INFO/top_level.txt
eggs/pytz-2025.2-py3.10.egg/EGG-INFO/LICENSE.txt
eggs/pytz-2025.2-py3.10.egg/EGG-INFO/top_level.txt
eggs/six-1.17.0-py3.10.egg/EGG-INFO/top_level.txt
eggs/transaction-5.0-py3.10.egg/EGG-INFO/LICENSE.txt
eggs/transaction-5.0-py3.10.egg/EGG-INFO/requires.txt
eggs/transaction-5.0-py3.10.egg/EGG-INFO/top_level.txt
eggs/z3c.coverage-2.1.0-py3.10.egg/EGG-INFO/SOURCES.txt
eggs/z3c.coverage-2.1.0-py3.10.egg/EGG-INFO/dependency_links.txt
eggs/z3c.coverage-2.1.0-py3.10.egg/EGG-INFO/entry_points.txt
eggs/z3c.coverage-2.1.0-py3.10.egg/EGG-INFO/namespace_packages.txt
eggs/z3c.coverage-2.1.0-py3.10.egg/EGG-INFO/requires.txt
eggs/z3c.coverage-2.1.0-py3.10.egg/EGG-INFO/top_level.txt
eggs/z3c.coverage-2.1.0-py3.10.egg/z3c/coverage/README.txt
eggs/zc.recipe.egg-2.0.7-py3.10.egg/EGG-INFO/SOURCES.txt
eggs/zc.recipe.egg-2.0.7-py3.10.egg/EGG-INFO/dependency_links.txt
