Metadata-Version: 2.1
Name: p01.cdn
Version: 1.3.6
Summary: Meta directive for register offload resource for Zope3
Home-page: http://pypi.python.org/pypi/p01.cdn
Author: Roger Ineichen, Projekt01 GmbH
Author-email: dev@projekt01.ch
License: ZPL 2.1
Keywords: zope3 z3c i18n cdn offload resource meta configuration directive
Platform: UNKNOWN
Classifier: Development Status :: 5 - Production/Stable
Classifier: Environment :: Web Environment
Classifier: Intended Audience :: Developers
Classifier: License :: OSI Approved :: Zope Public License
Classifier: Programming Language :: Python
Classifier: Natural Language :: English
Classifier: Operating System :: OS Independent
Classifier: Topic :: Internet :: WWW/HTTP
Classifier: Framework :: Zope3
Provides-Extra: test
